ipatel/__init__.py
ipatel/asn.py
ipatel/cli.py
ipatel/enrich.py
ipatel/utils.py
ipatel-0.1.4.dist-info/licenses/LICENSE
ipatel-0.1.4.dist-info/METADATA
ipatel-0.1.4.dist-info/WHEEL
ipatel-0.1.4.dist-info/entry_points.txt
ipatel-0.1.4.dist-info/top_level.txt
ipatel-0.1.4.dist-info/RECORD
