Metadata-Version: 2.4
Name: ipatel
Version: 0.1.4
Summary: A Python IP enrichment library
Author-email: Chethan Patel <chethanpatel100@gmail.com>
Project-URL: Homepage, https://github.com/Chethanpatel/ipatel
Project-URL: Documentation, https://Chethanpatel.github.io/ipatel/
Requires-Python: >=3.7
License-File: LICENSE
Requires-Dist: rich
Dynamic: license-file
